{
  "project_info": {
    "project_number": "635923857962",
    "project_id": "dongkap",
    "storage_bucket": "dongkap.appspot.com"
  },
  "client": [
    {
      "client_info": {
        "mobilesdk_app_id": "1:635923857962:android:c8a89ff2771ede7890f953",
        "android_client_info": {
          "package_name": "com.dongkap.do_dart"
        }
      },
      "oauth_client": [
        {
          "client_id": "635923857962-iedtekbo6o985k69b6hi31bllhvno2dl.apps.googleusercontent.com",
          "client_type": 1,
          "android_info": {
            "package_name": "com.dongkap.do_dart",
            "certificate_hash": "24777eabe2e683a2d23ed0b8b890b44f3f4d1367"
          }
        },
        {
          "client_id": "635923857962-co20kj5j0df4etlinb9m8b8bcad1h3m5.apps.googleusercontent.com",
          "client_type": 3
        }
      ],
      "api_key": [
        {
          "current_key": "AIzaSyDw0odhLbgYJ-sMAFXGe3ZwbclqqrtbEq4"
        }
      ],
      "services": {
        "appinvite_service": {
          "other_platform_oauth_client": [
            {
              "client_id": "635923857962-co20kj5j0df4etlinb9m8b8bcad1h3m5.apps.googleusercontent.com",
              "client_type": 3
            }
          ]
        }
      }
    },
    {
      "client_info": {
        "mobilesdk_app_id": "1:635923857962:android:7023af0b450abc8a90f953",
        "android_client_info": {
          "package_name": "com.dongkap.do_quran"
        }
      },
      "oauth_client": [
        {
          "client_id": "635923857962-4rsnbgoonpe8p9t90u5v2nsv8r8uufn1.apps.googleusercontent.com",
          "client_type": 1,
          "android_info": {
            "package_name": "com.dongkap.do_quran",
            "certificate_hash": "24777eabe2e683a2d23ed0b8b890b44f3f4d1367"
          }
        },
        {
          "client_id": "635923857962-co20kj5j0df4etlinb9m8b8bcad1h3m5.apps.googleusercontent.com",
          "client_type": 3
        }
      ],
      "api_key": [
        {
          "current_key": "AIzaSyDw0odhLbgYJ-sMAFXGe3ZwbclqqrtbEq4"
        }
      ],
      "services": {
        "appinvite_service": {
          "other_platform_oauth_client": [
            {
              "client_id": "635923857962-co20kj5j0df4etlinb9m8b8bcad1h3m5.apps.googleusercontent.com",
              "client_type": 3
            }
          ]
        }
      }
    }
  ],
  "configuration_version": "1"
}